generador_aleatorio/__init__.py
generador_aleatorio/frases.py
generador_aleatorio/generador.py
generador_aleatorio_31277312-0.1.0.dist-info/WHEEL
generador_aleatorio_31277312-0.1.0.dist-info/METADATA
generador_aleatorio_31277312-0.1.0.dist-info/RECORD
